JDSPackage/JDSPackage.py
JDSPackage/__init__.py
JDSPackage-1.0.0.dist-info/AUTHORS.rst
JDSPackage-1.0.0.dist-info/LICENSE
JDSPackage-1.0.0.dist-info/METADATA
JDSPackage-1.0.0.dist-info/WHEEL
JDSPackage-1.0.0.dist-info/top_level.txt
JDSPackage-1.0.0.dist-info/RECORD
