Metadata-Version: 2.1
Name: JDSPackage
Version: 1.0.0
Summary: documentation for first package
Home-page: https://github.com/jdsmithwes/JDSPackage
Author: Jamaal Darius Smith
Author-email: jdsmith1906@gmail.com
License: GNU General Public License v3
Keywords: JDSPackage
Platform: UNKNOWN
Classifier: Development Status :: 2 - Pre-Alpha
Classifier: Intended Audience :: Developers
Classifier: License :: OSI Approved :: GNU General Public License v3 (GPLv3)
Classifier: Natural Language :: English
Classifier: Programming Language :: Python :: 3.5
Classifier: Programming Language :: Python :: 3.6
Requires-Python: >=3.5
